{"decoder":{"specifications":{"electrical":{"maxTotalCurrent":1.1,"maxMotorCurrent":1.5,"maxVoltage":24,"peakCurrent":0},"dimensions":{"width":13.9,"height":2.9,"length":24.6},"connectors":{"list":"Cable;NEM652+Cable"}},"name":"T145","type":0,"manufacturerId":157,"manufacturerExtendedId":0,"articleNumbers":"81710;81720","decoderDBLink":"https://www.decoderdb.de/?decoderPage=51","typeIds":"","images":[{"name":"T145-1.png","copyright":"https://www.jaray.ch"}]},"version":{"createdBy":"DecoderDB","creatorLink":"https://www.decoderdb.de","author":"Stephan Bauer","lastUpdate":"2025-03-05T10:09:55.360Z","created":"2017-01-02T00:00:00.000"}}