{
  "decoder": {
    "name": "MS450",
    "type": "loco-sound",
    "typeIds": "6",
    "articleNumbers": "MS450;MS450R;MS450P22;MS450P16",
    "manufacturerId": 145,
    "manufacturerExtendedId": 0,
    "specifications": {
      "connectors": {
        "list": "Cable;NEM652+Cable;Plux12;Plux16"
      },
      "dimensions": {
        "width": 15,
        "height": 4,
        "length": 30
      },
      "electrical": {
        "peakCurrent": 2.5,
        "maxMotorCurrent": 1.2,
        "maxTotalCurrent": 1.2,
        "maxVoltage": 24,
        "functionOutputs": 10
      }
    },
    "options": "",
    "images": [
      {
        "name": "MS450-1.jpg",
        "copyright": ""
      },
      {
        "name": "ZIMO-MS450P22_bottom_HD.jpg",
        "lastModified": "2020-04-28T23:53:40",
        "copyright": "Zimo"
      },
      {
        "name": "ZIMO-MS450P22_top_HD.jpg",
        "lastModified": "2020-04-28T23:53:43",
        "copyright": "Zimo"
      }
    ],
    "decoderDBLink": "https://decoderdb.bidib.org/#/decoders/view/145/MS450"
  },
  "version": {
    "created": "2024-12-25T00:00:00.000",
    "lastUpdate": "2026-03-09T20:58:24.985Z"
  }
}